odoo8_addon_stock_picking_reorder_lines-8.0.0.1.0.99.dev24-nspkg.pth
odoo_addons/stock_picking_reorder_lines/README.rst
odoo_addons/stock_picking_reorder_lines/__init__.py
odoo_addons/stock_picking_reorder_lines/__openerp__.py
odoo_addons/stock_picking_reorder_lines/procurement.py
odoo_addons/stock_picking_reorder_lines/stock.py
odoo_addons/stock_picking_reorder_lines/stock_view.xml
odoo_addons/stock_picking_reorder_lines/i18n/ar.po
odoo_addons/stock_picking_reorder_lines/i18n/bg.po
odoo_addons/stock_picking_reorder_lines/i18n/bs.po
odoo_addons/stock_picking_reorder_lines/i18n/ca.po
odoo_addons/stock_picking_reorder_lines/i18n/cs.po
odoo_addons/stock_picking_reorder_lines/i18n/da.po
odoo_addons/stock_picking_reorder_lines/i18n/da_DK.po
odoo_addons/stock_picking_reorder_lines/i18n/de.po
odoo_addons/stock_picking_reorder_lines/i18n/en_GB.po
odoo_addons/stock_picking_reorder_lines/i18n/es.po
odoo_addons/stock_picking_reorder_lines/i18n/es_AR.po
odoo_addons/stock_picking_reorder_lines/i18n/es_CL.po
odoo_addons/stock_picking_reorder_lines/i18n/es_CO.po
odoo_addons/stock_picking_reorder_lines/i18n/es_CR.po
odoo_addons/stock_picking_reorder_lines/i18n/es_DO.po
odoo_addons/stock_picking_reorder_lines/i18n/es_EC.po
odoo_addons/stock_picking_reorder_lines/i18n/es_MX.po
odoo_addons/stock_picking_reorder_lines/i18n/es_PE.po
odoo_addons/stock_picking_reorder_lines/i18n/es_PY.po
odoo_addons/stock_picking_reorder_lines/i18n/es_VE.po
odoo_addons/stock_picking_reorder_lines/i18n/et.po
odoo_addons/stock_picking_reorder_lines/i18n/eu.po
odoo_addons/stock_picking_reorder_lines/i18n/fa.po
odoo_addons/stock_picking_reorder_lines/i18n/fi.po
odoo_addons/stock_picking_reorder_lines/i18n/fr.po
odoo_addons/stock_picking_reorder_lines/i18n/gl.po
odoo_addons/stock_picking_reorder_lines/i18n/he.po
odoo_addons/stock_picking_reorder_lines/i18n/hr.po
odoo_addons/stock_picking_reorder_lines/i18n/hu.po
odoo_addons/stock_picking_reorder_lines/i18n/id.po
odoo8_addon_stock_picking_reorder_lines-8.0.0.1.0.99.dev24.dist-info/METADATA
odoo8_addon_stock_picking_reorder_lines-8.0.0.1.0.99.dev24.dist-info/WHEEL
odoo8_addon_stock_picking_reorder_lines-8.0.0.1.0.99.dev24.dist-info/namespace_packages.txt
odoo8_addon_stock_picking_reorder_lines-8.0.0.1.0.99.dev24.dist-info/top_level.txt
odoo8_addon_stock_picking_reorder_lines-8.0.0.1.0.99.dev24.dist-info/RECORD
