Metadata-Version: 2.1
Name: odoo8-addon-stock-picking-reorder-lines
Version: 8.0.0.1.0.99.dev24
Summary: Provide a new field on stock moves, allowing to manage the orders of moves in a picking.
Home-page: http://www.camptocamp.com
Author: Camptocamp,Odoo Community Association (OCA)
Author-email: support@odoo-community.org
License: AGPL-3
Platform: UNKNOWN
Classifier: Programming Language :: Python
Classifier: Framework :: Odoo
Classifier: License :: OSI Approved :: GNU Affero General Public License v3
Requires-Python: ~=2.7
Requires-Dist: odoo (<9.0a,>=8.0a)
